wayfire/__init__.py
wayfire/ipc.py
wayfire/core/__init__.py
wayfire/core/template.py
wayfire/extra/ipc_utils.py
wayfire/extra/stipc.py
wayfire/extra/wpe.py
wayfire-3.2.dist-info/METADATA
wayfire-3.2.dist-info/WHEEL
wayfire-3.2.dist-info/top_level.txt
wayfire-3.2.dist-info/RECORD
