Metadata-Version: 2.4
Name: wayfire
Version: 3.2
Summary: wayfire compositor library
Author-email: Thiago <systemofdown@gmail.com>, Ilia Bozhinov <ammen99@gmail.com>
Project-URL: Homepage, https://github.com/WayfireWM/pywayfire
Project-URL: Issues, https://github.com/WayfireWM/pywayfire
Classifier: Programming Language :: Python :: 3
Classifier: License :: OSI Approved :: MIT License
Requires-Python: >=3.8
Provides-Extra: extras
